palb_py-0.1.2.dist-info/METADATA
palb_py-0.1.2.dist-info/WHEEL
palb_py-0.1.2.dist-info/entry_points.txt
palb_py/__init__.py
palb_py/_core.abi3.so
palb_py-0.1.2.dist-info/RECORD
