Metadata-Version: 2.4
Name: palb-py
Version: 0.1.2
Requires-Dist: numpy
Summary: A fast and exact method for solving least absolute deviations line problems (Affine-linear L1 regression).
Home-Page: https://github.com/SV-97/piecewise-affine-lower-bounding/palb
Author-email: Stefan Volz <volzstefan97@googlemail.com>
Requires-Python: >=3.12
